alias/__init__.py
alias/alias.py
alias_windows-1.1.1.dist-info/LICENSE.md
alias_windows-1.1.1.dist-info/METADATA
alias_windows-1.1.1.dist-info/WHEEL
alias_windows-1.1.1.dist-info/entry_points.txt
alias_windows-1.1.1.dist-info/top_level.txt
alias_windows-1.1.1.dist-info/RECORD
