Metadata-Version: 2.1
Name: alias-windows
Version: 1.1.1
Summary: Manage command aliases in Windows
Home-page: https://github.com/alexesprit/alias
Author: alexesprit
License: MIT
Platform: UNKNOWN
Classifier: Programming Language :: Python :: 3
Classifier: License :: OSI Approved :: MIT License
Classifier: Operating System :: Microsoft :: Windows
Requires-Python: >=3.6
